libra/__init__.py
libra/service.py
libra/core/__init__.py
libra/core/config.py
libra/core/exceptions.py
libra/core/models.py
libra/embedding/__init__.py
libra/embedding/aws_bedrock.py
libra/embedding/azure_openai.py
libra/embedding/base.py
libra/embedding/custom.py
libra/embedding/factory.py
libra/embedding/gemini.py
libra/embedding/huggingface.py
libra/embedding/local.py
libra/embedding/ollama.py
libra/embedding/openai.py
libra/embedding/together.py
libra/ingestion/__init__.py
libra/ingestion/base.py
libra/ingestion/chunker.py
libra/ingestion/directory.py
libra/ingestion/markdown.py
libra/ingestion/text.py
libra/interfaces/__init__.py
libra/interfaces/api.py
libra/interfaces/cli.py
libra/interfaces/mcp_server.py
libra/interfaces/web/__init__.py
libra/interfaces/web/routes.py
libra/interfaces/web/static/css/style.css
libra/interfaces/web/templates/add_context.html
libra/interfaces/web/templates/audit.html
libra/interfaces/web/templates/base.html
libra/interfaces/web/templates/context_detail.html
libra/interfaces/web/templates/contexts.html
libra/interfaces/web/templates/dashboard.html
libra/interfaces/web/templates/delete_context.html
libra/interfaces/web/templates/edit_context.html
libra/interfaces/web/templates/settings.html
libra/librarian/__init__.py
libra/librarian/base.py
libra/librarian/budget.py
libra/librarian/hybrid.py
libra/librarian/llm.py
libra/librarian/llm_generic.py
libra/librarian/rules.py
libra/llm_providers/__init__.py
libra/llm_providers/anthropic.py
libra/llm_providers/aws_bedrock.py
libra/llm_providers/azure_openai.py
libra/llm_providers/base.py
libra/llm_providers/custom.py
libra/llm_providers/factory.py
libra/llm_providers/gemini.py
libra/llm_providers/huggingface.py
libra/llm_providers/ollama.py
libra/llm_providers/openai.py
libra/llm_providers/together.py
libra/storage/__init__.py
libra/storage/database.py
libra/utils/__init__.py
libra/utils/logging.py
libra/utils/tokens.py
libra_context-0.1.0.2.dist-info/METADATA
libra_context-0.1.0.2.dist-info/WHEEL
libra_context-0.1.0.2.dist-info/entry_points.txt
libra_context-0.1.0.2.dist-info/licenses/LICENSE
libra_context-0.1.0.2.dist-info/RECORD
