Metadata-Version: 2.4
Name: libra-context
Version: 0.1.0.2
Summary: Intelligent Context Orchestration for AI Agents
Project-URL: Homepage, https://github.com/andrewmoshu/libra-context
Project-URL: Documentation, https://github.com/andrewmoshu/libra-context
Project-URL: Repository, https://github.com/andrewmoshu/libra-context
Author-email: Andrii Moshurenko <moshurenkoaa@gmail.com>
License: Business Source License 1.1
License-File: LICENSE
Keywords: ai,context,embedding,knowledge-base,llm,mcp,rag
Classifier: Development Status :: 3 - Alpha
Classifier: Intended Audience :: Developers
Classifier: License :: Other/Proprietary License
Classifier: Programming Language :: Python :: 3
Classifier: Programming Language :: Python :: 3.11
Classifier: Programming Language :: Python :: 3.12
Classifier: Topic :: Scientific/Engineering :: Artificial Intelligence
Requires-Python: >=3.11
Requires-Dist: aiofiles>=24.0.0
Requires-Dist: fastapi>=0.115.0
Requires-Dist: google-genai>=1.53.0
Requires-Dist: jinja2>=3.1.0
Requires-Dist: mcp>=1.0.0
Requires-Dist: pydantic>=2.10.0
Requires-Dist: python-multipart>=0.0.17
Requires-Dist: pyyaml>=6.0
Requires-Dist: rich>=13.9.0
Requires-Dist: sqlite-vec>=0.1.0
Requires-Dist: tiktoken>=0.8.0
Requires-Dist: typer>=0.15.0
Requires-Dist: uvicorn[standard]>=0.32.0
Provides-Extra: dev
Requires-Dist: black>=24.0.0; extra == 'dev'
Requires-Dist: mypy>=1.10.0; extra == 'dev'
Requires-Dist: pytest-asyncio>=0.23.0; extra == 'dev'
Requires-Dist: pytest>=8.0.0; extra == 'dev'
Requires-Dist: ruff>=0.5.0; extra == 'dev'
Provides-Extra: local
Requires-Dist: sentence-transformers>=3.0.0; extra == 'local'
